pyemo/__init__.py
pyemo/emo_gen.py
pyemo-0.0.3.dist-info/METADATA
pyemo-0.0.3.dist-info/WHEEL
pyemo-0.0.3.dist-info/top_level.txt
pyemo-0.0.3.dist-info/RECORD
