Metadata-Version: 2.1
Name: pyemo
Version: 0.0.3
Summary: Emoji based semantic scoped debuging 
Home-page: https://github.com/teal-finance/emo
Author: Teal Finance
Author-email: Teal.Finance@pm.me
License: UNKNOWN
Keywords: debuging,emoji
Platform: UNKNOWN
Classifier: Development Status :: 3 - Alpha
Classifier: Intended Audience :: Developers
Classifier: License :: OSI Approved :: MIT License
Classifier: Programming Language :: Python :: 3.8
